panoptipy/__init__.py
panoptipy/__main__.py
panoptipy/checks.py
panoptipy/cli.py
panoptipy/config.py
panoptipy/core.py
panoptipy/meta.py
panoptipy/rating.py
panoptipy/registry.py
panoptipy/reporters/__init__.py
panoptipy/reporters/base_reporter.py
panoptipy/reporters/console.py
panoptipy/reporters/json.py
panoptipy/reporters/parquet.py
panoptipy-0.0.9.dist-info/licenses/LICENSE
panoptipy-0.0.9.dist-info/METADATA
panoptipy-0.0.9.dist-info/WHEEL
panoptipy-0.0.9.dist-info/entry_points.txt
panoptipy-0.0.9.dist-info/top_level.txt
panoptipy-0.0.9.dist-info/RECORD
