Metadata-Version: 2.4
Name: panoptipy
Version: 0.0.9
Summary: A Python package for static code quality assessment
Author-email: Arthur Turrell <anon@anon.gmail.com>
License-Expression: MIT
Classifier: Development Status :: 4 - Beta
Classifier: Programming Language :: Python :: 3.10
Classifier: Programming Language :: Python :: 3.11
Classifier: Programming Language :: Python :: 3.12
Classifier: Programming Language :: Python :: 3.13
Requires-Python: >=3.10
License-File: LICENSE
Requires-Dist: click>=8.1.8
Requires-Dist: complexipy>=0.4.0
Requires-Dist: gitpython>=3.1.44
Requires-Dist: loguru>=0.7.3
Requires-Dist: nbstripout>=0.8.1
Requires-Dist: pandas>=2.2.3
Requires-Dist: pluggy>=1.5.0
Requires-Dist: pre-commit>=4.2.0
Requires-Dist: pyarrow>=19.0.1
Requires-Dist: pydoclint>=0.6.6
Requires-Dist: pytest>=8.3.5
Requires-Dist: quartodoc>=0.9.1
Requires-Dist: rich>=14.0.0
Requires-Dist: ruff>=0.11.5
Requires-Dist: sqlfluff>=3.4.2
Requires-Dist: toml>=0.10.2
Requires-Dist: validate-pyproject[all]>=0.24.1
Dynamic: license-file
